statlance/__init__.py
statlance/core/__init__.py
statlance/core/featuring.py
statlance/core/stats.py
statlance/core/viz.py
statlance/utils/__init__.py
statlance/utils/helper_functions.py
tests/__init__.py
tests/test_featuring.py
tests/test_stats.py
tests/test_viz.py
statlance-0.1.1.dist-info/LICENSE.md
statlance-0.1.1.dist-info/METADATA
statlance-0.1.1.dist-info/WHEEL
statlance-0.1.1.dist-info/entry_points.txt
statlance-0.1.1.dist-info/top_level.txt
statlance-0.1.1.dist-info/RECORD
