Metadata-Version: 2.1
Name: statlance
Version: 0.1.1
Summary: A Python library for EDA, visualization, and dashboarding
Home-page: https://github.com/databulance/statlance
Author: Databulance
Author-email: admin@databulance.com
Classifier: Programming Language :: Python :: 3
Classifier: License :: OSI Approved :: GNU General Public License v3 (GPLv3)
Classifier: Operating System :: OS Independent
License-File: LICENSE.md
Requires-Dist: streamlit
Requires-Dist: pygwalker ==0.4.8.1
Requires-Dist: openpyxl
Requires-Dist: numpy
Requires-Dist: pandas
Requires-Dist: scikit-learn
Requires-Dist: seaborn
Requires-Dist: matplotlib
Requires-Dist: xgboost
Requires-Dist: joblib
Requires-Dist: sqlalchemy
Requires-Dist: plotly
Provides-Extra: dev
Requires-Dist: pytest >=7.0 ; extra == 'dev'
Requires-Dist: twine >=4.0.2 ; extra == 'dev'
